ScoreTest/ScoreTest.py
ScoreTest/__init__.py
ScoreTest-0.0.2.dist-info/LICENSE
ScoreTest-0.0.2.dist-info/METADATA
ScoreTest-0.0.2.dist-info/WHEEL
ScoreTest-0.0.2.dist-info/top_level.txt
ScoreTest-0.0.2.dist-info/RECORD
