Metadata-Version: 2.1
Name: ScoreTest
Version: 0.0.2
Summary: 异常值检验方法——score检验统计量
Home-page: https://github.com/Bob-Annette/ScoreTest
Author: WangJing
Author-email: 615964325@qq.com
License: UNKNOWN
Platform: UNKNOWN
Classifier: Programming Language :: Python :: 3.9
Classifier: License :: OSI Approved :: MIT License
Classifier: Operating System :: OS Independent
Requires-Python: >=3.6
License-File: LICENSE
